{"version":1,"resource":"file:///home/bbd/snap/react-app/src/components/ThemeButton/index.js","entries":[{"id":"X9j7.js","timestamp":1661179166978},{"id":"oVDI.js","timestamp":1661179178405},{"id":"X5WQ.js","timestamp":1661179196357},{"id":"x7JD.js","timestamp":1661179214292},{"id":"BbO3.js","timestamp":1661179252475},{"id":"L5lw.js","timestamp":1661179268930},{"id":"tuPJ.js","timestamp":1661179386087},{"id":"dmSs.js","timestamp":1661179466378},{"id":"0GNJ.js","timestamp":1661179512097},{"id":"WIzY.js","timestamp":1661179621757},{"id":"ol7M.js","timestamp":1661180003909},{"id":"Kjjt.js","timestamp":1661180573863},{"id":"5vtg.js","timestamp":1661180839647},{"id":"iBnM.js","timestamp":1661180949604},{"id":"5C53.js","timestamp":1661181039182},{"id":"qpC3.js","source":"moved.source","timestamp":1661181063866},{"id":"21qQ.js","source":"moved.source","timestamp":1661181078382},{"id":"RQOp.js","timestamp":1661181843002},{"id":"AAlA.js","timestamp":1661181918892},{"id":"4AqS.js","timestamp":1661181976209},{"id":"Drzn.js","timestamp":1661182089839},{"id":"rPKF.js","timestamp":1661182117091},{"id":"hiu9.js","timestamp":1661182141292},{"id":"CkoH.js","timestamp":1661182625604},{"id":"dwwF.js","timestamp":1661182660093},{"id":"zAhI.js","timestamp":1661182702186},{"id":"e91Z.js","timestamp":1661182755519},{"id":"hbaY.js","timestamp":1661182771343},{"id":"8Bcm.js","timestamp":1661183101497},{"id":"U7OU.js","timestamp":1661247718985}]}